conda_env_replicator.py
conda_env_replicator-0.1.3.dist-info/LICENSE
conda_env_replicator-0.1.3.dist-info/METADATA
conda_env_replicator-0.1.3.dist-info/WHEEL
conda_env_replicator-0.1.3.dist-info/entry_points.txt
conda_env_replicator-0.1.3.dist-info/top_level.txt
conda_env_replicator-0.1.3.dist-info/RECORD
