Metadata-Version: 2.1
Name: conda-env-replicator
Version: 0.1.3
Summary: Create portable conda environment files for OS/glibc upgrades
Author-email: Omar Valerio <omar.valerio@mpinb.mpg.de>
Maintainer-email: Omar Valerio <omar.valerio@mpinb.mpg.de>
License: MIT
Project-URL: Homepage, https://github.com/mpinb/conda-env-replicator
Project-URL: Repository, https://github.com/mpinb/conda-env-replicator
Project-URL: Documentation, https://github.com/mpinb/conda-env-replicator#readme
Project-URL: Bug Tracker, https://github.com/mpinb/conda-env-replicator/issues
Keywords: conda,environment,migration,HPC,glibc,CUDA,portability
Classifier: Development Status :: 4 - Beta
Classifier: Intended Audience :: Science/Research
Classifier: Intended Audience :: Developers
Classifier: Intended Audience :: System Administrators
Classifier: License :: OSI Approved :: MIT License
Classifier: Operating System :: POSIX :: Linux
Classifier: Programming Language :: Python :: 3
Classifier: Programming Language :: Python :: 3.7
Classifier: Programming Language :: Python :: 3.8
Classifier: Programming Language :: Python :: 3.9
Classifier: Programming Language :: Python :: 3.10
Classifier: Programming Language :: Python :: 3.11
Classifier: Programming Language :: Python :: 3.12
Classifier: Topic :: Software Development :: Build Tools
Classifier: Topic :: System :: Installation/Setup
Classifier: Topic :: System :: Systems Administration
Requires-Python: >=3.7
License-File: LICENSE
Requires-Dist: PyYAML>=5.1
Provides-Extra: dev
Requires-Dist: pytest>=7.0; extra == "dev"
Requires-Dist: pytest-cov>=4.0; extra == "dev"
Requires-Dist: black>=22.0; extra == "dev"
Requires-Dist: flake8>=5.0; extra == "dev"
Requires-Dist: mypy>=0.990; extra == "dev"
Requires-Dist: build>=0.10; extra == "dev"
Requires-Dist: twine>=4.0; extra == "dev"
Requires-Dist: validate-pyproject[all]>=0.12; extra == "dev"
